vprof/__init__.py
vprof/__main__.py
vprof/base_profiler.py
vprof/code_heatmap.py
vprof/flame_graph.py
vprof/memory_profiler.py
vprof/profiler.py
vprof/runner.py
vprof/stats_server.py
vprof/ui/favicon.ico
vprof/ui/profile.html
vprof/ui/vprof_min.js
vprof/ui/css/code_heatmap.css
vprof/ui/css/flame_graph.css
vprof/ui/css/memory_stats.css
vprof/ui/css/profiler.css
vprof/ui/css/progress.gif
vprof/ui/css/vprof.css
vprof-0.38.dist-info/LICENSE
vprof-0.38.dist-info/METADATA
vprof-0.38.dist-info/WHEEL
vprof-0.38.dist-info/entry_points.txt
vprof-0.38.dist-info/top_level.txt
vprof-0.38.dist-info/RECORD
