Metadata-Version: 2.1
Name: vprof
Version: 0.38
Summary: Visual profiler for Python
Home-page: http://github.com/nvdv/vprof
Author: nvdv
Author-email: aflatnine@gmail.com
License: BSD
Keywords: debugging,profiling
Platform: UNKNOWN
Classifier: Development Status :: 3 - Alpha
Classifier: Environment :: Web Environment
Classifier: Intended Audience :: Developers
Classifier: Programming Language :: Python
Classifier: Programming Language :: Python :: 3
Classifier: Topic :: Software Development
Requires-Dist: psutil (>=3)
